autogluon.fair-0.1-py3.8-nspkg.pth
autogluon/fair/__init__.py
autogluon/fair/version.py
autogluon/fair/learners/__init__.py
autogluon/fair/learners/efficient_compute.py
autogluon/fair/learners/fair.py
autogluon/fair/learners/fair_frontier.py
autogluon/fair/utils/__init__.py
autogluon/fair/utils/group_metric_classes.py
autogluon/fair/utils/group_metrics.py
autogluon.fair-0.1.dist-info/LICENSE
autogluon.fair-0.1.dist-info/METADATA
autogluon.fair-0.1.dist-info/WHEEL
autogluon.fair-0.1.dist-info/namespace_packages.txt
autogluon.fair-0.1.dist-info/top_level.txt
autogluon.fair-0.1.dist-info/zip-safe
autogluon.fair-0.1.dist-info/RECORD
