Metadata-Version: 2.1
Name: autogluon.fair
Version: 0.1
Summary: AutoML Framework for evaluating ML model fairness metrics
Home-page: https://github.com/autogluon/autogluon-fair
Author: AutoGluon Community
License: Apache-2.0
Project-URL: Documentation, https://auto.gluon.ai
Project-URL: Bug Reports, https://github.com/autogluon/autogluon-fair/issues
Project-URL: Source, https://github.com/autogluon/autogluon-fair/
Project-URL: Contribute!, https://github.com/autogluon/autogluon-fair/blob/master/CONTRIBUTING.md
Platform: UNKNOWN
Classifier: Development Status :: 4 - Beta
Classifier: Intended Audience :: Education
Classifier: Intended Audience :: Developers
Classifier: Intended Audience :: Science/Research
Classifier: Intended Audience :: Customer Service
Classifier: Intended Audience :: Financial and Insurance Industry
Classifier: Intended Audience :: Healthcare Industry
Classifier: Intended Audience :: Telecommunications Industry
Classifier: License :: OSI Approved :: Apache Software License
Classifier: Operating System :: MacOS
Classifier: Operating System :: Microsoft :: Windows
Classifier: Operating System :: POSIX
Classifier: Operating System :: Unix
Classifier: Programming Language :: Python :: 3
Classifier: Programming Language :: Python :: 3.8
Classifier: Programming Language :: Python :: 3.9
Classifier: Programming Language :: Python :: 3.10
Classifier: Topic :: Software Development
Classifier: Topic :: Scientific/Engineering :: Artificial Intelligence
Classifier: Topic :: Scientific/Engineering :: Information Analysis
Classifier: Topic :: Scientific/Engineering :: Image Recognition
Requires-Python: >=3.8, <3.11
Requires-Dist: autogluon.common (<1.0,>=0.7)
Requires-Dist: autogluon.core (<1.0,>=0.7)
Requires-Dist: autogluon.tabular[all] (<1.0,>=0.7)
Requires-Dist: autogluon.features (<1.0,>=0.7)
Requires-Dist: numpy (<2.0,>=1.21.4)
Requires-Dist: pandas (<2.0,>=1.2.5)
Provides-Extra: tests
Requires-Dist: pytest-cov ; extra == 'tests'
Requires-Dist: pytest ; extra == 'tests'
Requires-Dist: tox ; extra == 'tests'
